bunnycdn_storage/__init__.py
bunnycdn_storage/storage.py
bunnycdn_storage_handler-0.1.1.dist-info/LICENSE
bunnycdn_storage_handler-0.1.1.dist-info/METADATA
bunnycdn_storage_handler-0.1.1.dist-info/WHEEL
bunnycdn_storage_handler-0.1.1.dist-info/top_level.txt
bunnycdn_storage_handler-0.1.1.dist-info/RECORD
