Metadata-Version: 2.2
Name: bunnycdn-storage-handler
Version: 0.1.1
Summary: A Python client for BunnyCDN Storage API
Home-page: https://github.com/Ahmedwaleed22/bunnycdn-storage-handler
Author: Ahmed Waleed
Author-email: work@ahmedwaleed.net
Classifier: Programming Language :: Python :: 3
Classifier: License :: OSI Approved :: MIT License
Classifier: Operating System :: OS Independent
Requires-Python: >=3.6
License-File: LICENSE
Requires-Dist: requests>=2.25.1
Requires-Dist: aiohttp>=3.8.0
Requires-Dist: tqdm>=4.65.0
Dynamic: author
Dynamic: author-email
Dynamic: classifier
Dynamic: description
Dynamic: description-content-type
Dynamic: home-page
Dynamic: requires-dist
Dynamic: requires-python
Dynamic: summary
